[
 {
  "docstatus": 0,
  "doctype": "Available Locker",
  "locker": "LC01",
  "modified": "2025-07-08 10:30:15.989463",
  "name": "LC01"
 },
 {
  "docstatus": 0,
  "doctype": "Available Locker",
  "locker": "LC02",
  "modified": "2025-07-08 10:30:24.632556",
  "name": "LC02"
 },
 {
  "docstatus": 0,
  "doctype": "Available Locker",
  "locker": "L001",
  "modified": "2025-07-09 15:25:39.749570",
  "name": "L001"
 },
 {
  "docstatus": 0,
  "doctype": "Available Locker",
  "locker": "L002",
  "modified": "2025-07-09 15:25:39.797562",
  "name": "L002"
 },
 {
  "docstatus": 0,
  "doctype": "Available Locker",
  "locker": "L003",
  "modified": "2025-07-09 15:25:39.830500",
  "name": "L003"
 },
 {
  "docstatus": 0,
  "doctype": "Available Locker",
  "locker": "L004",
  "modified": "2025-07-09 15:25:39.854944",
  "name": "L004"
 },
 {
  "docstatus": 0,
  "doctype": "Available Locker",
  "locker": "L005",
  "modified": "2025-07-09 15:25:39.878307",
  "name": "L005"
 },
 {
  "docstatus": 0,
  "doctype": "Available Locker",
  "locker": "L006",
  "modified": "2025-07-09 15:25:39.895174",
  "name": "L006"
 },
 {
  "docstatus": 0,
  "doctype": "Available Locker",
  "locker": "L007",
  "modified": "2025-07-09 15:25:39.911514",
  "name": "L007"
 },
 {
  "docstatus": 0,
  "doctype": "Available Locker",
  "locker": "L008",
  "modified": "2025-07-09 15:25:39.928421",
  "name": "L008"
 },
 {
  "docstatus": 0,
  "doctype": "Available Locker",
  "locker": "L009",
  "modified": "2025-07-09 15:25:39.944914",
  "name": "L009"
 },
 {
  "docstatus": 0,
  "doctype": "Available Locker",
  "locker": "L010",
  "modified": "2025-07-09 15:25:39.964138",
  "name": "L010"
 },
 {
  "docstatus": 0,
  "doctype": "Available Locker",
  "locker": "L011",
  "modified": "2025-07-09 15:25:39.988397",
  "name": "L011"
 },
 {
  "docstatus": 0,
  "doctype": "Available Locker",
  "locker": "L012",
  "modified": "2025-07-09 15:25:40.014118",
  "name": "L012"
 },
 {
  "docstatus": 0,
  "doctype": "Available Locker",
  "locker": "L013",
  "modified": "2025-07-09 15:25:40.038831",
  "name": "L013"
 },
 {
  "docstatus": 0,
  "doctype": "Available Locker",
  "locker": "L014",
  "modified": "2025-07-09 15:25:40.064223",
  "name": "L014"
 },
 {
  "docstatus": 0,
  "doctype": "Available Locker",
  "locker": "L015",
  "modified": "2025-07-09 15:25:40.097314",
  "name": "L015"
 },
 {
  "docstatus": 0,
  "doctype": "Available Locker",
  "locker": "L016",
  "modified": "2025-07-09 15:25:40.122355",
  "name": "L016"
 },
 {
  "docstatus": 0,
  "doctype": "Available Locker",
  "locker": "L017",
  "modified": "2025-07-09 15:25:40.147708",
  "name": "L017"
 },
 {
  "docstatus": 0,
  "doctype": "Available Locker",
  "locker": "L018",
  "modified": "2025-07-09 15:25:40.172425",
  "name": "L018"
 },
 {
  "docstatus": 0,
  "doctype": "Available Locker",
  "locker": "L019",
  "modified": "2025-07-09 15:25:40.205316",
  "name": "L019"
 },
 {
  "docstatus": 0,
  "doctype": "Available Locker",
  "locker": "L020",
  "modified": "2025-07-09 15:25:40.231326",
  "name": "L020"
 },
 {
  "docstatus": 0,
  "doctype": "Available Locker",
  "locker": "L021",
  "modified": "2025-07-09 15:25:40.305424",
  "name": "L021"
 },
 {
  "docstatus": 0,
  "doctype": "Available Locker",
  "locker": "L022",
  "modified": "2025-07-09 15:25:40.331158",
  "name": "L022"
 },
 {
  "docstatus": 0,
  "doctype": "Available Locker",
  "locker": "L023",
  "modified": "2025-07-09 15:25:40.355505",
  "name": "L023"
 },
 {
  "docstatus": 0,
  "doctype": "Available Locker",
  "locker": "L024",
  "modified": "2025-07-09 15:25:40.381015",
  "name": "L024"
 },
 {
  "docstatus": 0,
  "doctype": "Available Locker",
  "locker": "L025",
  "modified": "2025-07-09 15:25:40.405980",
  "name": "L025"
 },
 {
  "docstatus": 0,
  "doctype": "Available Locker",
  "locker": "L026",
  "modified": "2025-07-09 15:25:40.431303",
  "name": "L026"
 },
 {
  "docstatus": 0,
  "doctype": "Available Locker",
  "locker": "L027",
  "modified": "2025-07-09 15:25:40.456119",
  "name": "L027"
 },
 {
  "docstatus": 0,
  "doctype": "Available Locker",
  "locker": "L028",
  "modified": "2025-07-09 15:25:40.480967",
  "name": "L028"
 },
 {
  "docstatus": 0,
  "doctype": "Available Locker",
  "locker": "L029",
  "modified": "2025-07-09 15:25:40.506057",
  "name": "L029"
 },
 {
  "docstatus": 0,
  "doctype": "Available Locker",
  "locker": "L030",
  "modified": "2025-07-09 15:25:40.531146",
  "name": "L030"
 }
]