[
 {
  "address": "USA",
  "contact": "+91-1234567890",
  "docstatus": 0,
  "doctype": "TrainerReg",
  "email": "arnold@gmail.com",
  "gender": "Male",
  "modified": "2025-07-11 18:23:15.098103",
  "name": "T-011",
  "name1": "arnold schwarzenegger",
  "specialization": "1"
 },
 {
  "address": "USA",
  "contact": "+91-1234567890",
  "docstatus": 0,
  "doctype": "TrainerReg",
  "email": "adam@gmail.com",
  "gender": "Male",
  "modified": "2025-07-11 18:24:14.064432",
  "name": "T-012",
  "name1": "Adam Neiffer",
  "specialization": "2"
 },
 {
  "address": "USA",
  "contact": "+91-1234567890",
  "docstatus": 0,
  "doctype": "TrainerReg",
  "email": "chris@gmail.com",
  "gender": "Male",
  "modified": "2025-07-11 18:25:20.743766",
  "name": "T-013",
  "name1": "Chris Heria",
  "specialization": "3"
 },
 {
  "address": "India",
  "contact": "+91-1234567890",
  "docstatus": 0,
  "doctype": "TrainerReg",
  "email": "vijay@gmail.com",
  "gender": "Male",
  "modified": "2025-07-11 18:26:24.835706",
  "name": "T-014",
  "name1": "Shri Vijay Sharma",
  "specialization": "4"
 },
 {
  "address": "Kalyan",
  "contact": "+91-1234567890",
  "docstatus": 0,
  "doctype": "TrainerReg",
  "email": "sahana@gmail.com",
  "gender": "Male",
  "modified": "2025-07-11 18:27:31.623720",
  "name": "T-015",
  "name1": "Sahana Jagnatha",
  "specialization": "5"
 },
 {
  "address": "Germany",
  "contact": "+91-1234567890",
  "docstatus": 0,
  "doctype": "TrainerReg",
  "email": "mike@gmail.com",
  "gender": "Male",
  "modified": "2025-07-11 18:28:39.379840",
  "name": "T-016",
  "name1": "Mike Passenier",
  "specialization": "6"
 },
 {
  "address": "Russia",
  "contact": "+91-1234567890",
  "docstatus": 0,
  "doctype": "TrainerReg",
  "email": "kabib@gmail.com",
  "gender": "Male",
  "modified": "2025-07-11 18:29:08.584616",
  "name": "T-017",
  "name1": "Kabib",
  "specialization": "7"
 }
]